Metadata-Version: 2.1
Name: rpyc-ikernel
Version: 0.4.0
Summary: rpyc for jupyter kernel
Home-page: https://github.com/sipeed/rpyc_ikernel
Author: Juwan
Author-email: juwan@sipeed.com
License: BSD
Platform: UNKNOWN
Classifier: Programming Language :: Python :: 3
Classifier: Framework :: IPython
Classifier: License :: OSI Approved :: BSD License
